{
  "ticker": "CDNS",
  "company": "Cadence Design Systems, Inc.",
  "sector": "Technology",
  "price": {
    "current": 337.01,
    "open": 339.06,
    "high": 346.33,
    "low": 334.59,
    "previous_close": 344.64,
    "change_pct": -2.21,
    "market_cap": 92952756224
  },
  "trade_parameters": {
    "buy_above": 337.01,
    "stop_loss": 320.07,
    "take_profit": 361.48,
    "expected_move": "\u00b17.26%",
    "expected_move_dollars": "\u00b1$24.47",
    "risk_reward": 1.44,
    "support_levels": [
      375.94,
      373.54,
      366.99
    ],
    "resistance_levels": [
      365.01,
      383.8,
      387.19
    ],
    "expected_return_pct": 7.26,
    "max_drawdown_pct": -5.03
  },
  "scores": {
    "technical": 71,
    "fundamental": 64,
    "options": 90,
    "sentiment": 70,
    "historical": 50,
    "macro": 65,
    "overall": 69.8
  },
  "historical_score_breakdown": {
    "simple": 50,
    "deep": 50,
    "merged": 50,
    "has_deep": false
  },
  "technical": {
    "trend": {
      "ema_20": 363.11,
      "sma_50": 373.63,
      "sma_100": 338.79,
      "sma_200": 327.92,
      "price_above_20_ema": "False",
      "price_above_50_sma": "False",
      "price_above_200_sma": "True",
      "golden_cross": false,
      "death_cross": false
    },
    "momentum": {
      "rsi_14": 30.64,
      "macd": -9.1537,
      "macd_signal": -4.0463,
      "macd_histogram": -5.1074,
      "stochastic_rsi": 24.98,
      "adx": 27.59,
      "momentum_score": "weak"
    },
    "volume": {
      "obv_trend": "down",
      "volume_trend": "above_avg"
    },
    "volatility": {
      "historical_volatility_20": 43.68,
      "historical_volatility_60": 45.08
    },
    "price_structure": {
      "resistance": [
        365.01,
        383.8,
        387.19
      ],
      "support": [
        375.94,
        373.54,
        366.99
      ],
      "high_20d": 391.0,
      "high_30d": 406.67,
      "high_52w": 416.69,
      "distance_to_resistance_pct": 8.31,
      "distance_to_support_pct": 5.03,
      "nearest_resistance": 365.01,
      "nearest_support": 320.07
    }
  },
  "fundamentals": {
    "revenue_growth_yoy": 14.12,
    "eps_growth_yoy": 5.45,
    "gross_margin": 86.08,
    "operating_margin": 29.7,
    "net_margin": 21.18,
    "roe": 20.66,
    "debt_to_equity": 46.99,
    "current_ratio": 1.47,
    "cash": 1546153984,
    "total_debt": 3083354112,
    "net_cash": -1537200128,
    "forward_pe": 35.84,
    "peg_ratio": 3.27,
    "ev_ebitda": 46.91,
    "price_to_sales": 16.81
  },
  "options": {
    "implied_volatility": 0.2531,
    "put_call_ratio": 0.66,
    "call_volume": 1038,
    "put_volume": 685,
    "call_open_interest": 1840,
    "put_open_interest": 2344,
    "expected_move": 24.46,
    "expected_move_pct": 7.26,
    "atm_straddle_price": null,
    "skew": "mild_call_skew",
    "gamma_exposure": "positive",
    "unusual_activity": "True"
  },
  "analyst": {
    "buy_ratings": 26,
    "hold_ratings": 0,
    "sell_ratings": 0,
    "avg_price_target": 395.94,
    "target_high": 470.0,
    "target_low": 275.0,
    "target_median": 400.0,
    "consensus_trend": "strong_buy",
    "recent_upgrades": [],
    "recent_downgrades": [],
    "number_of_analysts": 26
  },
  "historical_earnings": {},
  "historical_analysis": null,
  "news": {
    "sentiment_score": 0.5,
    "headline_count": 10,
    "key_themes": [],
    "major_events": [],
    "bullish_signals": 0,
    "bearish_signals": 0
  },
  "market_regime": {
    "sp500_trend": "bullish",
    "sp500_price": 747.41,
    "sp500_change_pct": -0.12,
    "nasdaq_trend": "bearish",
    "nasdaq_price": 705.35,
    "nasdaq_change_pct": -0.51,
    "vix": 17.75,
    "vix_trend": "rising",
    "market_regime": "neutral",
    "risk_level": "moderate",
    "sector_leadership": [],
    "macro_events": [],
    "breadth": "healthy",
    "macro_score": 65,
    "regime_assessment": {
      "regime": "neutral",
      "confidence": 50.0,
      "sp500_trend": "bullish",
      "nasdaq_trend": "bearish",
      "vix": 17.75,
      "market_regime": "neutral"
    }
  },
  "decision": "AVOID",
  "decision_rationale": "positive options flow",
  "earnings_date": "2026-07-27",
  "days_until_earnings": 4,
  "earnings_time": "unknown"
}