{
  "ticker": "CPNG",
  "company": "Coupang, Inc.",
  "sector": "Consumer Cyclical",
  "price": {
    "current": 16.44,
    "open": 16.4,
    "high": 16.56,
    "low": 15.96,
    "previous_close": 16.62,
    "change_pct": -1.08,
    "market_cap": 29510856704
  },
  "trade_parameters": {
    "buy_above": 16.71,
    "stop_loss": 15.96,
    "take_profit": 17.38,
    "expected_move": "\u00b15.7%",
    "expected_move_dollars": "\u00b1$0.94",
    "risk_reward": 0.89,
    "support_levels": [
      19.83,
      16.92,
      16.9
    ],
    "resistance_levels": [
      16.71,
      16.91,
      19.53
    ],
    "expected_return_pct": 3.99,
    "max_drawdown_pct": -4.49
  },
  "scores": {
    "technical": 55,
    "fundamental": 67,
    "options": 87,
    "sentiment": 70,
    "historical": 50,
    "macro": 50,
    "overall": 64.3
  },
  "historical_score_breakdown": {
    "simple": 50,
    "deep": 50,
    "merged": 50,
    "has_deep": false
  },
  "technical": {
    "trend": {
      "ema_20": 17.59,
      "sma_50": 16.97,
      "sma_100": 18.3,
      "sma_200": 21.84,
      "price_above_20_ema": "False",
      "price_above_50_sma": "False",
      "price_above_200_sma": "False",
      "golden_cross": false,
      "death_cross": false
    },
    "momentum": {
      "rsi_14": 40.44,
      "macd": -0.0716,
      "macd_signal": 0.1836,
      "macd_histogram": -0.2552,
      "stochastic_rsi": 0.0,
      "adx": 19.51,
      "momentum_score": "weak"
    },
    "volume": {
      "obv_trend": "down",
      "volume_trend": "above_avg"
    },
    "volatility": {
      "historical_volatility_20": 42.56,
      "historical_volatility_60": 62.11
    },
    "price_structure": {
      "resistance": [
        16.71,
        16.91,
        19.53
      ],
      "support": [
        19.83,
        16.92,
        16.9
      ],
      "high_20d": 19.53,
      "high_30d": 19.6,
      "high_52w": 34.08,
      "distance_to_resistance_pct": 1.64,
      "distance_to_support_pct": 2.92,
      "nearest_resistance": 16.71,
      "nearest_support": 15.96
    }
  },
  "fundamentals": {
    "revenue_growth_yoy": 14.09,
    "eps_growth_yoy": 37.5,
    "gross_margin": 28.81,
    "operating_margin": -2.85,
    "net_margin": -0.47,
    "roe": -3.99,
    "debt_to_equity": 137.3,
    "current_ratio": 0.97,
    "cash": 6301000192,
    "total_debt": 5395999744,
    "net_cash": 905000448,
    "forward_pe": 56.79,
    "peg_ratio": 0.45,
    "ev_ebitda": 44.7,
    "price_to_sales": 0.84
  },
  "options": {
    "implied_volatility": 0.1988,
    "put_call_ratio": 0.23,
    "call_volume": 9282,
    "put_volume": 2169,
    "call_open_interest": 11024,
    "put_open_interest": 5241,
    "expected_move": 0.94,
    "expected_move_pct": 5.7,
    "atm_straddle_price": null,
    "skew": "mild_call_skew",
    "gamma_exposure": "positive",
    "unusual_activity": "True"
  },
  "analyst": {
    "buy_ratings": 18,
    "hold_ratings": 0,
    "sell_ratings": 0,
    "avg_price_target": 25.89,
    "target_high": 36.0,
    "target_low": 12.0,
    "target_median": 26.5,
    "consensus_trend": "buy",
    "recent_upgrades": [],
    "recent_downgrades": [],
    "number_of_analysts": 18
  },
  "historical_earnings": {},
  "historical_analysis": null,
  "news": {
    "sentiment_score": 0.5,
    "headline_count": 10,
    "key_themes": [],
    "major_events": [],
    "bullish_signals": 0,
    "bearish_signals": 0
  },
  "market_regime": {
    "sp500_trend": "neutral",
    "sp500_price": 742.09,
    "sp500_change_pct": -0.16,
    "nasdaq_trend": "bearish",
    "nasdaq_price": 696.06,
    "nasdaq_change_pct": 0.1,
    "vix": 17.74,
    "vix_trend": "rising",
    "market_regime": "neutral",
    "risk_level": "moderate",
    "sector_leadership": [],
    "macro_events": [],
    "breadth": "healthy",
    "macro_score": 50,
    "regime_assessment": {
      "regime": "unfavorable",
      "confidence": 25.0,
      "sp500_trend": "neutral",
      "nasdaq_trend": "bearish",
      "vix": 17.74,
      "market_regime": "neutral"
    }
  },
  "decision": "AVOID",
  "decision_rationale": "positive options flow",
  "earnings_date": "2026-08-04",
  "days_until_earnings": 14,
  "earnings_time": "unknown"
}